Binary/__init__.py
Binary/elf.py
Binary/elf2.py
Crypto/__init__.py
Crypto/caesar.py
Crypto/cutils.py
Crypto/rsa.py
Deprecated/__init__.py
Deprecated/nullfuz.py
Deprecated/nullproc_handler.py
Gentools/__init__.py
Gentools/debruijn.py
Testing/__init__.py
Testing/elf3test.py
Testing/elftest.py
Testing/quicktest.py
fcfuzz-0.1.0.dist-info/DESCRIPTION.rst
fcfuzz-0.1.0.dist-info/METADATA
fcfuzz-0.1.0.dist-info/RECORD
fcfuzz-0.1.0.dist-info/WHEEL
fcfuzz-0.1.0.dist-info/metadata.json
fcfuzz-0.1.0.dist-info/top_level.txt
