Metadata-Version: 2.0
Name: fcfuzz
Version: 0.1.0
Summary: python3 based computer security suite
Home-page: UNKNOWN
Author: nullp0inter
Author-email: nicetry@fbi.gov
License: None
Keywords: nullp0nter fcfuzz
Platform: UNKNOWN
